setup.py
dist_hamon/Binomialdistribution.py
dist_hamon/Gaussiandistribution.py
dist_hamon/Generaldistribution.py
dist_hamon/__init__.py
dist_hamon.egg-info/PKG-INFO
dist_hamon.egg-info/SOURCES.txt
dist_hamon.egg-info/dependency_links.txt
dist_hamon.egg-info/not-zip-safe
dist_hamon.egg-info/top_level.txt