Metadata-Version: 1.0
Name: dist-hamon
Version: 0.1
Summary: Gaussian and Binomial distributions
Home-page: UNKNOWN
Author: Hadong Lee
Author-email: hadongme@gmail.com
License: UNKNOWN
Platform: UNKNOWN
